simulaix/__init__.py
simulaix/__main__.py
simulaix-0.0.2.dist-info/METADATA
simulaix-0.0.2.dist-info/WHEEL
simulaix-0.0.2.dist-info/entry_points.txt
simulaix-0.0.2.dist-info/licenses/LICENSE
simulaix-0.0.2.dist-info/RECORD
